{
  "updatedAt": "2018-04-08T12:43:14.562Z",
  "ACL": {
    "*": {
      "read": true
    },
    "5902984044d904006912043d": {
      "write": true
    }
  },
  "content": "# Preface\nIn order to practice English, try to write articles in English. Syntax error, please correct me Email: liangtongzhuo@gmail.com\n\nImplemeation of several step.\n\n# 1. Simple construction\n```\nfunction Promise1(fn) {\n  var doneCallback;\n  this.then = function (done) {\n    doneCallback = done;\n    return this;\n  }\n  function resolve(value) {\n    doneCallback(value);\n  }\n  fn(resolve);\n}\n```\n\n# 2. Add chain support, async callback\n```\nfunction Promise2(fn) {\n  var doneList = [];\n  this.then = function (done, fail) {\n    doneList.push(done);\n    return this;\n  }\n  function resolve(value) {\n    setTimeout(function () {\n      doneList.forEach(function (fulfill) {\n        fulfill(value);\n      });\n    }, 0);\n  }\n  fn(resolve);\n}\n```\n\n# 3. Addition state judgment\n```\nfunction Promise3(fn) {\n  var state = 'pending';\n  var doneList = [];\n  this.then = function (done) {\n    switch (state) {\n      case \"pending\":\n        doneList.push(done);\n        return this;\n        break;\n      case 'fulfilled':\n        done();\n        return this;\n        break;\n    }\n  };\n  function resolve(value) {\n    setTimeout(function () {\n      state = \"fulfilled\";\n      doneList.forEach(function (fulfill) {\n        fulfill(value);\n      });\n    }, 0);\n  };\n  fn(resolve);\n}\n```\n\n# 4. Plus result transfer.\n```\nfunction Promise4(fn) {\n  var state = 'pending';\n  var doneList = [];\n  this.then = function (done) {\n    switch (state) {\n      case \"pending\":\n        doneList.push(done);\n        return this;\n        break;\n      case 'fulfilled':\n        done();\n        return this;\n        break;\n    }\n  };\n\n  function resolve(newValue) {\n    setTimeout(function () {\n      state = \"fulfilled\";\n      let value = newValue;\n      doneList.forEach((fulfill) => {\n        value = fulfill(value);\n      });\n    }, 0);\n  };\n  fn(resolve);\n}\n```\n\n# 5. Support serial.\n```\nfunction Promise5(fn) {\n  var state = 'pending';\n  var doneList = [];\n  this.then = function (done) {\n    switch (state) {\n      case \"pending\":\n        doneList.push(done);\n        return this;\n        break;\n      case 'fulfilled':\n        done();\n        return this;\n        break;\n    }\n  };\n\n  function resolve(newValue) {\n    setTimeout(function () {\n      state = \"fulfilled\";\n      let value = newValue;\n      for (var i = 0; i < doneList.length; i++) {\n        var temp = doneList[i](value)\n        if (temp instanceof Promise5) {\n          var newP = temp;\n          for (i++; i < doneList.length; i++) {\n            newP.then(doneList[i]);\n          }\n        } else {\n          value = temp;\n        }\n      }\n    }, 0);\n  };\n  fn(resolve);\n}\n```\n\n# 6. Join reject support.\n\n```\nfunction Promise6(fn) {\n  var state = 'pending';\n  var doneList = [];\n  var failList = [];\n  this.then = function (done, fail) {\n    switch (state) {\n      case \"pending\":\n        doneList.push(done);\n        failList.push(fail || null);\n        return this;\n        break;\n      case 'fulfilled':\n        done();\n        return this;\n        break;\n      case 'rejected':\n        fail();\n        return this;\n        break;\n    }\n  }\n  function resolve(newValue) {\n    setTimeout(function () {\n      state = \"fulfilled\";\n      var value = newValue;\n      for (var i = 0; i < doneList.length; i++) {\n        var temp = doneList[i](value);\n        if (temp instanceof Promise) {\n          var newP = temp;\n          for (i++; i < doneList.length; i++) {\n            newP.then(doneList[i], failList[i]);\n          }\n        } else {\n          value = temp;\n        }\n      }\n    }, 0);\n  }\n  function reject(newValue) {\n    setTimeout(function () {\n      state = \"rejected\";\n      var value = newValue;\n      var tempRe = failList[0](value);\n      if (tempRe instanceof Promise) {\n        var newP = tempRe;\n        for (i = 1; i < doneList.length; i++) {\n          newP.then(doneList[i], failList[i]);\n        }\n      } else {\n        value = tempRe;\n        doneList.shift();\n        failList.shift();\n        resolve(value);\n      }\n    }, 0);\n  }\n  fn(resolve, reject);\n}\n\n```\n\n# The method is realized.\n```\nconst promise = new Promise6((resolve, reject) => {\n  setTimeout(() => {\n    resolve(111);\n  })\n});\n\npromise\n  .then((value) => {\n    return new Promise((resolve) => {\n      setTimeout(() => {\n        console.log('p2拿到前面传入的值：' + value)\n        resolve('p2的结果');\n      }, 100);\n    });\n  }, (value) => {\n    console.log(value); \n    return 'p then方法第一次错误的返回';\n  })\n  .then((value) => {\n    console.log(value);\n  })\n\n```\n\n# There is a standard promise\nhttps://github.com/xieranmaya/blog/issues/3\n\n\n\n\n",
  "createdAt": "2018-04-06T10:42:24.268Z",
  "title": "Simple \"Promise\" implementation",
  "tag": "JavaScript"
}