{
  "updatedAt": "2026-02-26T07:44:59.763Z",
  "ACL": {
    "*": {
      "read": true
    },
    "5902984044d904006912043d": {
      "write": true
    }
  },
  "content": "没想到，LeanCloud 竟然真的关闭了。\n这家云服务商，算是一路陪伴我技术成长的“老同学”。\n\n刚开始接触技术时，我主要写一些移动端前端相关的内容，那时候最头疼的就是后端搭建——服务器部署、域名购买，每一步都繁琐又复杂。就在我手足无措的时候，LeanCloud 出现了，它的解决方案像为我量身定做，完美解决了我的痛点。\n\n后来，我研究 LeanCloud 的官方文档，它做得十分细致，我也借着这份文档，学会了全栈开发和架构相关的知识。\n\n工作后，我依然习惯把很多创业项目部署在 LeanCloud 上，更多的是一种偏爱。\n\n如今 AI 简化了基础配置和代码编写，我的博客也会用 AI 迁移成静态文档，和这段技术时光温柔告别。\n\n",
  "createdAt": "2026-02-26T07:36:31.583Z",
  "title": "LeanCloud 关闭",
  "tag": "AI 润色"
}